nester.py
nester_with_fileObject-1.0.0.dist-info/METADATA
nester_with_fileObject-1.0.0.dist-info/WHEEL
nester_with_fileObject-1.0.0.dist-info/top_level.txt
nester_with_fileObject-1.0.0.dist-info/RECORD
