Metadata-Version: 2.1
Name: nester_with_fileObject
Version: 1.0.0
Summary: Printing each items in list (nested or not) on new line with or without required tab spaces and the data will be sent to the required file or output screen depending on the file object argument
Home-page: 
Author: SonaM
Author-email: sonalimetkar1@gmail.com
